[
  {"name": "Покраска стен", "specialist_type": "Маляр", "unit": "м²"},
  {"name": "Покраска потолка", "specialist_type": "Маляр", "unit": "м²"},
  {"name": "Шпаклевка стен", "specialist_type": "Штукатур", "unit": "м²"},
  {"name": "Укладка ламината", "specialist_type": "Укладчик", "unit": "м²"},
  {"name": "Укладка плитки", "specialist_type": "Плиточник", "unit": "м²"},
  {"name": "Электромонтаж", "specialist_type": "Электрик", "unit": "точка"},
  {"name": "Штробление", "specialist_type": "Электрик", "unit": "м"},
  {"name": "Сантехнические работы", "specialist_type": "Сантехник", "unit": "точка"},
  {"name": "Прокладка кабеля", "specialist_type": "Электрик", "unit": "м"},
  {"name": "Монтаж розетки", "specialist_type": "Электрик", "unit": "шт"},
  {"name": "Монтаж светильника", "specialist_type": "Электрик", "unit": "шт"},
  {"name": "Монтаж труб", "specialist_type": "Сантехник", "unit": "м"}
]
